{
  "applicationId": "com.stellantis.erpfiat",
  "defaultMode": "window",
  "version": "1.0.0",

  "cli": {
    "binaryName": "ERPFiat",
    "resourcesPath": "/resources/",
    "extensionsPath": "/extensions/",
    "clientLibrary": "/resources/js/neutralino.js",
    "binaryVersion": "5.3.0",
    "clientVersion": "3.11.0"
  },

  "modes": {
    "window": {
      "title": "ERP Fiat — Sistema Intranet",
      "width": 1280,
      "height": 800,
      "minWidth": 900,
      "minHeight": 600,
      "center": true,
      "maximize": true,
      "icon": "/resources/favicon.png"
    }
  },

  "documentRoot": "/resources/",
  "url": "/kpi/kpi.html",
  "enableServer": true,
  "enableNativeAPI": true,
  "tokenSecurity": "one-time",

  "logging": {
    "enabled": true,
    "writeToLogFile": true
  },

  "nativeAllowList": [
    "app.*",
    "os.*",
    "storage.*",
    "filesystem.*",
    "window.*",
    "debug.*"
  ],

  "serverHeaders": {
    "Access-Control-Allow-Origin": "*",
    "Access-Control-Allow-Methods": "GET, POST, PUT, DELETE, OPTIONS",
    "Access-Control-Allow-Headers": "*",
    "Content-Security-Policy": "default-src * 'unsafe-inline' 'unsafe-eval' data: blob:; connect-src * data: blob:; script-src * 'unsafe-inline' 'unsafe-eval'; img-src * data: blob:;"
  }
}